DESCRIPTION.rst
MANIFEST.in
setup.py
NominaFlora.egg-info/PKG-INFO
NominaFlora.egg-info/SOURCES.txt
NominaFlora.egg-info/dependency_links.txt
NominaFlora.egg-info/requires.txt
NominaFlora.egg-info/top_level.txt
nominaflora/NominaFlora.py
nominaflora/__init__.py
nominaflora/data/common_first.txt
nominaflora/data/common_second.txt
nominaflora/data/genus.txt
nominaflora/data/species.txt