Metadata-Version: 1.1
Name: NominaFlora
Version: 0.1.5
Summary: Generates new flower names
Home-page: https://github.com/mouse-reeve/nomina-flora
Author: Mouse Reeve
Author-email: mouse.reeve@gmail.com
License: MIT
Keywords: generative language flowers
Platform: UNKNOWN
Classifier: Development Status :: 3 - Alpha
Classifier: Intended Audience :: Developers
Classifier: Topic :: Artistic Software
Classifier: License :: OSI Approved :: MIT License
Classifier: Programming Language :: Python :: 2
Classifier: Programming Language :: Python :: 2.7
